{
    "updated_at": "2026-05-01",
    "data": [
        {
            "代號": "QQQ",
            "12月累積報酬": 40.76,
            "1月累積報酬": 19.61,
            "收盤價": 667.74,
            "200SMA": 603.3,
            "乖離率": 10.68
        },
        {
            "代號": "GLD",
            "12月累積報酬": 39.47,
            "1月累積報酬": 2.19,
            "收盤價": 423.66,
            "200SMA": 390.96,
            "乖離率": 8.37
        },
        {
            "代號": "VEA",
            "12月累積報酬": 31.79,
            "1月累積報酬": 10.91,
            "收盤價": 68.8,
            "200SMA": 62.53,
            "乖離率": 10.03
        },
        {
            "代號": "VXUS",
            "12月累積報酬": 31.65,
            "1月累積報酬": 11.3,
            "收盤價": 83.06,
            "200SMA": 75.78,
            "乖離率": 9.61
        },
        {
            "代號": "VWO",
            "12月累積報酬": 31.29,
            "1月累積報酬": 12.42,
            "收盤價": 58.93,
            "200SMA": 54.38,
            "乖離率": 8.36
        },
        {
            "代號": "VT",
            "12月累積報酬": 30.75,
            "1月累積報酬": 12.68,
            "收盤價": 151.2,
            "200SMA": 139.92,
            "乖離率": 8.06
        },
        {
            "代號": "VTI",
            "12月累積報酬": 30.58,
            "1月累積報酬": 13.64,
            "收盤價": 354.18,
            "200SMA": 330.16,
            "乖離率": 7.27
        },
        {
            "代號": "ACWI",
            "12月累積報酬": 30.53,
            "1月累積報酬": 12.93,
            "收盤價": 151.54,
            "200SMA": 140.2,
            "乖離率": 8.09
        },
        {
            "代號": "SPY",
            "12月累積報酬": 30.34,
            "1月累積報酬": 13.72,
            "收盤價": 718.66,
            "200SMA": 669.9,
            "乖離率": 7.28
        },
        {
            "代號": "BOXX",
            "12月累積報酬": 4.13,
            "1月累積報酬": 0.32,
            "收盤價": 116.53,
            "200SMA": 114.71,
            "乖離率": 1.58
        },
        {
            "代號": "BIL",
            "12月累積報酬": 2.64,
            "1月累積報酬": 0.29,
            "收盤價": 91.64,
            "200SMA": 91.11,
            "乖離率": 0.58
        },
        {
            "代號": "IEF",
            "12月累積報酬": 1.41,
            "1月累積報酬": 0.03,
            "收盤價": 94.98,
            "200SMA": 95.74,
            "乖離率": -0.79
        },
        {
            "代號": "IEI",
            "12月累積報酬": 1.39,
            "1月累積報酬": 0.14,
            "收盤價": 118.23,
            "200SMA": 118.75,
            "乖離率": -0.44
        },
        {
            "代號": "BTC-USD",
            "12月累積報酬": -18.98,
            "1月累積報酬": 14.44,
            "收盤價": 76323.77,
            "200SMA": 84205.02,
            "乖離率": -9.36
        },
        {
            "代號": "0050.TW",
            "12月累積報酬": NaN,
            "1月累積報酬": NaN,
            "收盤價": NaN,
            "200SMA": NaN,
            "乖離率": 0.0
        }
    ]
}